{"AFG":-1.9,"ALB":5.9,"DZA":-13.7,"ASM":18,"AND":-2.7,"AGO":-2.6,"AIA":22.9,"ATG":31.9,"ARG":-16.7,"ARM":-14.4,"AUS":12.6,"AUT":7.6,"AZE":-15.2,"BHS":4,"BHR":178.8,"BGD":5.3,"BLR":-7.4,"BEL":1.1,"BLZ":-6.3,"BEN":1.5,"BTN":7.4,"BOL":-0.4,"BIH":14.2,"BWA":-6.4,"BRA":2.8,"BRN":-3,"BGR":10.6,"BFA":-4.6,"BDI":-18.9,"KHM":-5.9,"CMR":9.1,"CAN":0.5,"CPV":-9.1,"CYM":-7.5,"CAF":5.8,"TCD":16.2,"CHL":-4,"CHN":-0.4,"COL":1,"COM":-25.1,"COG":4.7,"COK":0.7,"CRI":18.1,"CIV":9.1,"HRV":11.6,"CUB":2.4,"CYP":-43.6,"CZE":18.2,"COD":-7.5,"DNK":-10.7,"DJI":-5.4,"DOM":-14.9,"TLS":10.3,"ECU":3.7,"EGY":-57.9,"SLV":48.1,"GNQ":-4,"ERI":5.2,"EST":-0.9,"SWZ":2.8,"ETH":-7.9,"FLK":0.5,"FRO":-0.1,"FJI":-25.5,"FIN":-2.2,"FRA":-6,"PYF":-6,"GAB":6.1,"GMB":2.9,"GEO":-0.4,"DEU":6.2,"GHA":6.1,"GRC":-5.2,"GRL":-5,"GTM":16.9,"GIN":-8,"GNB":-11.4,"GUY":-12.6,"HTI":-9.9,"HMD":9,"HND":9,"HKG":-5,"HUN":12.1,"ISL":-4.5,"IND":2.9,"IDN":17.5,"IRN":2.4,"IRQ":-18.4,"IRL":-1.4,"IMN":-9.9,"ISR":-32.7,"ITA":-10.5,"JAM":-3.1,"JPN":-8,"JOR":-30.2,"KAZ":-14,"KEN":-16.1,"KIR":-48.2,"KWT":34.5,"KGZ":-1,"LAO":-1.6,"LVA":-4.7,"LBN":-30.8,"LSO":-1.8,"LBR":4.1,"LBY":-5.3,"LTU":0.6,"LUX":12.3,"MDG":-0.4,"MWI":-17.1,"MYS":15.9,"MLI":-7.8,"MRT":34.5,"MUS":31.8,"MEX":5.3,"MDA":0.4,"MNG":-10.3,"MNE":7.2,"MAR":-17.4,"MOZ":-11.9,"MMR":-1.7,"NAM":-24.6,"NPL":3.5,"NLD":-6.1,"NCL":-32.6,"NZL":13.5,"NIC":5.5,"NER":-22.4,"NGA":7.3,"PRK":3.1,"MKD":13.7,"NOR":4.8,"OMN":138.2,"PAK":19.6,"PSE":-35.6,"PAN":7.9,"PNG":11.4,"PRY":-1.6,"PER":-2.4,"PHL":19.2,"POL":-2.8,"PRT":-1.7,"PRI":-17,"QAT":204.7,"ROU":6.8,"RUS":4.1,"RWA":-18.4,"VCT":-6.6,"WSM":14,"STP":-9.6,"SAU":57.1,"SEN":0,"SRB":10.8,"SYC":-1.1,"SLE":-2.9,"SVK":3.1,"SVN":3.9,"SLB":2.2,"SOM":-4.9,"ZAF":3.6,"SGS":3.6,"KOR":-24.1,"SSD":-8.8,"ESP":-16.8,"LKA":-4.9,"SDN":-5.4,"SUR":-16.3,"SWE":-0.4,"CHE":8.7,"SYR":-29.1,"TJK":-15.9,"TZA":-20.4,"THA":6.8,"TGO":8.3,"TTO":-14.1,"TUN":2.3,"TUR":-1.2,"TKM":-19.2,"UGA":-13.7,"UKR":6.3,"ARE":83.6,"GBR":-6.1,"USA":6.6,"VIR":-15,"URY":-11.6,"UZB":-24.5,"VUT":-24.8,"VEN":-5.2,"VNM":-2.3,"YEM":5.8,"ZMB":-21.4,"ZWE":-22}