{"AFG":8.055,"ALB":1.725,"DZA":2.244,"AND":0.029,"AGO":20.02,"ATG":0.016,"ARG":21.358,"ARM":0.988,"ABW":0.001,"AUS":51.179,"AUT":11.91,"AZE":3.669,"BHS":0.014,"BHR":0.021,"BGD":39.572,"BRB":0.093,"BLR":39.158,"BEL":27.047,"BLZ":0.256,"BEN":-1.359,"BTN":0.646,"BOL":38.6,"BIH":4.159,"BWA":0.855,"BRA":52.456,"VGB":0.009,"BRN":0.055,"BGR":5.864,"BFA":1.528,"BDI":2.131,"KHM":6.341,"CMR":8.707,"CAN":97.447,"CPV":0.021,"CAF":1.211,"TCD":24.056,"CHL":10.172,"CHN":362.63,"COL":30.115,"COM":0.073,"COG":1.266,"COK":0.004,"CRI":2.521,"CIV":145.821,"HRV":3.38,"CUB":8.252,"CYP":0.448,"CZE":16.934,"COD":11.084,"DNK":10.509,"DJI":0.041,"DMA":0.039,"DOM":0.754,"TLS":1.132,"ECU":9.194,"EGY":4.227,"SLV":4.769,"GNQ":0.31,"ERI":0.177,"EST":10.173,"SWZ":0.247,"ETH":19.234,"FJI":0.447,"FIN":21.135,"FRA":109.217,"GAB":2.65,"GMB":0.241,"GEO":8.455,"DEU":94.637,"GHA":3.269,"GRC":8.384,"GRD":0.031,"GTM":9.922,"GIN":59.817,"GNB":0.608,"GUY":3.332,"HTI":2.607,"HND":7.674,"HKG":0.046,"HUN":15.098,"ISL":0.735,"IND":299.398,"IDN":251.117,"IRN":10.221,"IRQ":1.439,"IRL":35.252,"ISR":0.452,"ITA":30.419,"JAM":0.749,"JPN":23.443,"JOR":0.128,"KAZ":38.046,"KEN":6.298,"KIR":0.003,"KWT":0.057,"KGZ":3.125,"LAO":3.549,"LVA":9.857,"LBN":0.217,"LSO":0.21,"LBR":13.074,"LBY":0.332,"LIE":0.014,"LTU":18.575,"LUX":0.639,"MAC":0.01,"MDG":18.674,"MWI":0.909,"MYS":13.381,"MDV":0.002,"MLI":4.042,"MLT":0.042,"MRT":1.506,"MUS":0.13,"MEX":26.22,"FSM":0.017,"MDA":3.211,"MNG":19.28,"MNE":1.725,"MAR":4.644,"MOZ":3.398,"MMR":57.075,"NAM":0.666,"NRU":0,"NPL":8.847,"NLD":16.506,"NZL":16.773,"NIC":4.755,"NER":2.737,"NGA":10.615,"NIU":0.002,"PRK":12.792,"MKD":1.338,"NOR":13.94,"OMN":0.224,"PAK":17.694,"PLW":0.001,"PAN":2.854,"PNG":-0.545,"PRY":2.763,"PER":10.722,"PHL":54.949,"POL":64.995,"PRT":5.084,"QAT":0.027,"ROU":25.073,"RUS":547.219,"RWA":1.243,"SHN":0,"KNA":0.083,"LCA":0.01,"VCT":0.03,"WSM":0.073,"STP":0.094,"SAU":0.023,"SEN":2.298,"SRB":11.658,"SYC":0.003,"SLE":53.365,"SGP":0.559,"SVK":6.22,"SVN":1.452,"SLB":0.095,"SOM":3.503,"ZAF":4.248,"KOR":9.584,"SSD":5.243,"ESP":26.099,"LKA":14.54,"SDN":12.967,"SUR":0.274,"SWE":33.87,"CHE":5.391,"SYR":1.799,"TWN":1.281,"TJK":1.482,"TZA":6.809,"THA":20.059,"TGO":0.512,"TON":0.043,"TTO":0.701,"TUN":1.336,"TUR":20.703,"TKM":4.93,"TCA":0,"TUV":0.001,"UGA":8.246,"UKR":73.97,"ARE":0.087,"GBR":218.552,"USA":1056.119,"URY":9.018,"UZB":7.335,"VUT":0.128,"VEN":59.263,"VNM":34.067,"YEM":1.9,"ZMB":10.217,"ZWE":1.466}