{"AFG":369,"AGO":1115,"AIA":780,"ALB":1187,"AND":881,"ARE":52,"ARG":702,"ARM":882,"ASM":2533,"ATG":784,"AUS":449,"AUT":1316,"AZE":573,"BDI":2011,"BEL":893,"BEN":990,"BFA":623,"BGD":2061,"BGR":750,"BHR":75,"BHS":924,"BIH":1148,"BLR":723,"BLZ":1509,"BOL":1418,"BRA":1621,"BRN":3238,"BTN":3435,"BWA":430,"CAF":1108,"CAN":721,"CHE":1627,"CHL":1390,"CHN":862,"CIV":1179,"CMR":1689,"COD":1535,"COG":1517,"COK":1679,"COL":3092,"COM":1335,"CPV":152,"CRI":3112,"CUB":982,"CYM":1003,"CYP":384,"CZE":784,"DEU":807,"DJI":180,"DNK":908,"DOM":917,"DZA":55,"ECU":3284,"EGY":13,"ERI":298,"ESP":562,"EST":773,"ETH":1034,"FIN":817,"FJI":2446,"FRA":1092,"FRO":1063,"GAB":2134,"GBR":1129,"GEO":1273,"GHA":1093,"GIN":1589,"GMB":699,"GNB":1344,"GNQ":2980,"GRC":799,"GRL":483,"GTM":1806,"GUY":1987,"HKG":2069,"HMD":1424,"HND":1571,"HRV":1015,"HTI":815,"HUN":696,"IDN":3440,"IMN":1213,"IND":1254,"IRL":1175,"IRN":300,"IRQ":237,"ISL":1414,"ISR":202,"ITA":998,"JAM":1028,"JOR":79,"JPN":1959,"KAZ":344,"KEN":768,"KGZ":932,"KHM":1865,"KIR":1010,"KOR":1347,"KWT":131,"LAO":1958,"LBN":573,"LBR":2395,"LBY":20,"LKA":1884,"LSO":990,"LTU":736,"LUX":888,"LVA":762,"MAR":196,"MDA":514,"MDG":1420,"MEX":780,"MKD":705,"MLI":231,"MMR":2339,"MNE":1497,"MNG":281,"MOZ":865,"MRT":55,"MUS":1120,"MWI":1451,"MYS":3111,"NAM":281,"NCL":1539,"NER":94,"NGA":1055,"NIC":1809,"NLD":866,"NOR":1323,"NPL":2106,"NZL":1630,"OMN":56,"PAK":463,"PAN":3132,"PER":2126,"PHL":2932,"PNG":4485,"POL":735,"PRI":1030,"PRK":1201,"PRT":672,"PRY":1274,"PSE":306,"PYF":1731,"QAT":81,"ROU":719,"RUS":632,"RWA":1614,"SAU":70,"SDN":181,"SEN":460,"SLB":4435,"SLE":2598,"SLV":1512,"SOM":335,"SRB":703,"SSD":870,"STP":1563,"SUR":2017,"SVK":807,"SVN":1325,"SWE":851,"SWZ":843,"SYC":2076,"SYR":211,"TCD":311,"TGO":1232,"THA":1657,"TJK":737,"TKM":177,"TLS":1695,"TTO":1307,"TUN":163,"TUR":676,"TZA":1148,"UGA":1558,"UKR":638,"URY":1354,"USA":898,"UZB":250,"VCT":1037,"VEN":1978,"VIR":885,"VNM":2107,"VUT":2489,"WSM":3058,"YEM":163,"ZAF":477,"ZMB":1126,"ZWE":726}