{"AFG":334,"AGO":1151,"AIA":809,"ALB":1354,"AND":885,"ARE":41,"ARG":665,"ARM":824,"ASM":2699,"ATG":852,"AUS":474,"AUT":1286,"AZE":535,"BDI":1990,"BEL":933,"BEN":1062,"BFA":619,"BGD":2242,"BGR":738,"BHR":74,"BHS":905,"BIH":1159,"BLR":748,"BLZ":1529,"BOL":1347,"BRA":1633,"BRN":3294,"BTN":3573,"BWA":420,"CAF":1109,"CAN":748,"CHE":1626,"CHL":1385,"CHN":892,"CIV":1220,"CMR":1675,"COD":1507,"COG":1467,"COK":1833,"COL":3162,"COM":1449,"CPV":167,"CRI":3564,"CUB":969,"CYM":1030,"CYP":331,"CZE":851,"DEU":881,"DJI":278,"DNK":882,"DOM":1026,"DZA":50,"ECU":3335,"EGY":14,"ERI":338,"ESP":592,"EST":798,"ETH":1100,"FIN":785,"FJI":2542,"FRA":1112,"FRO":1070,"GAB":2134,"GBR":1108,"GEO":1283,"GHA":1123,"GIN":1701,"GMB":726,"GNB":1506,"GNQ":3035,"GRC":756,"GRL":513,"GTM":1841,"GUY":2137,"HKG":1978,"HMD":1446,"HND":1686,"HRV":1063,"HTI":945,"HUN":728,"IDN":3555,"IMN":1186,"IND":1438,"IRL":1192,"IRN":286,"IRQ":240,"ISL":1449,"ISR":184,"ITA":990,"JAM":1115,"JOR":75,"JPN":1902,"KAZ":346,"KEN":781,"KGZ":945,"KHM":1836,"KIR":962,"KOR":1209,"KWT":148,"LAO":2089,"LBN":548,"LBR":2423,"LBY":19,"LKA":2002,"LSO":1050,"LTU":789,"LUX":917,"LVA":804,"MAR":196,"MDA":555,"MDG":1376,"MEX":793,"MKD":790,"MLI":243,"MMR":2318,"MNE":1585,"MNG":309,"MOZ":888,"MRT":55,"MUS":1209,"MWI":1449,"MYS":3138,"NAM":270,"NCL":1522,"NER":110,"NGA":1100,"NIC":1907,"NLD":874,"NOR":1274,"NPL":2377,"NZL":1671,"OMN":55,"PAK":458,"PAN":3423,"PER":2166,"PHL":3033,"PNG":4551,"POL":786,"PRI":1140,"PRK":1245,"PRT":699,"PRY":1335,"PSE":280,"PYF":1697,"QAT":63,"ROU":754,"RUS":643,"RWA":1644,"SAU":68,"SDN":205,"SEN":466,"SLB":4423,"SLE":2703,"SLV":1564,"SOM":321,"SRB":785,"SSD":885,"STP":1657,"SUR":2134,"SVK":896,"SVN":1319,"SWE":835,"SWZ":879,"SYC":1976,"SYR":215,"TCD":298,"TGO":1246,"THA":1720,"TJK":681,"TKM":160,"TLS":1872,"TTO":1370,"TUN":159,"TUR":678,"TZA":1170,"UGA":1518,"UKR":637,"URY":1258,"USA":869,"UZB":237,"VCT":1079,"VEN":2042,"VIR":944,"VNM":2218,"VUT":2428,"WSM":3028,"YEM":185,"ZAF":474,"ZMB":1102,"ZWE":720}