{"quakes":[{"lon":-92.97,"lat":15.83,"depth":100,"mag":6.4,"place":"4 km SW of El Ramal (Porvenir), Mexico","time":852036102200,"url":"https://earthquake.usgs.gov/earthquakes/eventpage/usp0007v87"},{"lon":128.1,"lat":-3.99,"depth":33,"mag":6,"place":"33 km SSW of Ambon, Indonesia","time":851974912000,"url":"https://earthquake.usgs.gov/earthquakes/eventpage/usp0007v6w"},{"lon":138.94,"lat":-2.24,"depth":33,"mag":6.3,"place":"192 km WNW of Abepura, Indonesia","time":851633303290,"url":"https://earthquake.usgs.gov/earthquakes/eventpage/usp0007v14"},{"lon":138.92,"lat":43.21,"depth":227,"mag":6.5,"place":"131 km W of Iwanai, Japan","time":851266407620,"url":"https://earthquake.usgs.gov/earthquakes/eventpage/usp0007uuh"},{"lon":-30.04,"lat":0.87,"depth":10,"mag":6.7,"place":"central Mid-Atlantic Ridge","time":850206978700,"url":"https://earthquake.usgs.gov/earthquakes/eventpage/usp0007u7a"},{"lon":-42.85,"lat":29.85,"depth":10,"mag":6,"place":"northern Mid-Atlantic Ridge","time":850130928610,"url":"https://earthquake.usgs.gov/earthquakes/eventpage/usp0007u68"},{"lon":107.49,"lat":-7.94,"depth":51,"mag":6.1,"place":"82 km S of Banjar, Indonesia","time":850103656310,"url":"https://earthquake.usgs.gov/earthquakes/eventpage/usp0007u5k"},{"lon":-172.28,"lat":-18.35,"depth":33,"mag":6.2,"place":"183 km E of Neiafu, Tonga","time":849617816920,"url":"https://earthquake.usgs.gov/earthquakes/eventpage/usp0007tx6"},{"lon":131.31,"lat":31.79,"depth":49,"mag":6.7,"place":"17 km SW of Miyazaki, Japan","time":849565079240,"url":"https://earthquake.usgs.gov/earthquakes/eventpage/usp0007tw5"},{"lon":-179.68,"lat":-30.52,"depth":356,"mag":6.2,"place":"Kermadec Islands region","time":849481780590,"url":"https://earthquake.usgs.gov/earthquakes/eventpage/usp0007tur"},{"lon":-24.17,"lat":-1.22,"depth":10,"mag":6.3,"place":"central Mid-Atlantic Ridge","time":849216358850,"url":"https://earthquake.usgs.gov/earthquakes/eventpage/usp0007tpr"},{"lon":141.13,"lat":34.35,"depth":33,"mag":6.1,"place":"115 km SE of Katsuura, Japan","time":848456867980,"url":"https://earthquake.usgs.gov/earthquakes/eventpage/usp0007t8t"},{"lon":78.13,"lat":35.34,"depth":33,"mag":6.9,"place":"130 km ENE of Thang, India","time":848400286060,"url":"https://earthquake.usgs.gov/earthquakes/eventpage/usp0007t7m"},{"lon":-179.7,"lat":-22.2,"depth":592,"mag":6.1,"place":"south of the Fiji Islands","time":848265080270,"url":"https://earthquake.usgs.gov/earthquakes/eventpage/usp0007t5h"},{"lon":-86.05,"lat":11.08,"depth":33,"mag":6,"place":"27 km SW of San Juan del Sur, Nicaragua","time":848258261980,"url":"https://earthquake.usgs.gov/earthquakes/eventpage/usp0007t5e"},{"lon":-176.3,"lat":-15.1,"depth":33,"mag":6,"place":"201 km S of Mata-Utu, Wallis and Futuna","time":848137670840,"url":"https://earthquake.usgs.gov/earthquakes/eventpage/usp0007t3h"},{"lon":-176.62,"lat":-21.24,"depth":192,"mag":6.2,"place":"146 km W of Haveluloto, Tonga","time":847979258110,"url":"https://earthquake.usgs.gov/earthquakes/eventpage/usp0007t0s"},{"lon":166.46,"lat":-11.38,"depth":109,"mag":6,"place":"102 km SE of Lata, Solomon Islands","time":847958338510,"url":"https://earthquake.usgs.gov/earthquakes/eventpage/usp0007t09"},{"lon":-75.41,"lat":-15.47,"depth":33,"mag":6,"place":"29 km WSW of San Juan, Peru","time":847888329820,"url":"https://earthquake.usgs.gov/earthquakes/eventpage/usp0007syw"},{"lon":-75.69,"lat":-14.84,"depth":33,"mag":6.1,"place":"54 km WSW of Changuillo, Peru","time":847852899940,"url":"https://earthquake.usgs.gov/earthquakes/eventpage/usp0007sxw"},{"lon":-75.67,"lat":-14.99,"depth":33,"mag":7.7,"place":"60 km SW of Changuillo, Peru","time":847817984030,"url":"https://earthquake.usgs.gov/earthquakes/eventpage/usp0007swp"},{"lon":95.01,"lat":19.33,"depth":80,"mag":6,"place":"17 km W of Thayetmyo, Myanmar","time":847704147760,"url":"https://earthquake.usgs.gov/earthquakes/eventpage/usp0007suh"},{"lon":-179.05,"lat":-32.54,"depth":33,"mag":6.2,"place":"south of the Kermadec Islands","time":847673241140,"url":"https://earthquake.usgs.gov/earthquakes/eventpage/usp0007stz"},{"lon":126.34,"lat":9.79,"depth":33,"mag":6.1,"place":"25 km E of Union, Philippines","time":847347016710,"url":"https://earthquake.usgs.gov/earthquakes/eventpage/usp0007sk7"},{"lon":143.54,"lat":28,"depth":9,"mag":6.6,"place":"Bonin Islands, Japan region","time":847310458850,"url":"https://earthquake.usgs.gov/earthquakes/eventpage/usp0007sja"},{"lon":126.36,"lat":9.76,"depth":33,"mag":6,"place":"27 km E of Union, Philippines","time":847196985960,"url":"https://earthquake.usgs.gov/earthquakes/eventpage/usp0007sfq"},{"lon":180,"lat":-31.16,"depth":369,"mag":6.8,"place":"Kermadec Islands region","time":847186894770,"url":"https://earthquake.usgs.gov/earthquakes/eventpage/usp0007sfm"},{"lon":-77.39,"lat":7.31,"depth":14,"mag":6.3,"place":"33 km WSW of Riosucio, Colombia","time":847128297430,"url":"https://earthquake.usgs.gov/earthquakes/eventpage/usp0007seb"},{"lon":-173.23,"lat":66.99,"depth":20,"mag":6.1,"place":"179 km NNW of Lorino, Russia","time":846185513930,"url":"https://earthquake.usgs.gov/earthquakes/eventpage/usp0007rwf"},{"lon":-178.51,"lat":-20.41,"depth":591,"mag":6.9,"place":"Fiji region","time":845736828780,"url":"https://earthquake.usgs.gov/earthquakes/eventpage/usp0007rp1"},{"lon":131.47,"lat":31.89,"depth":22,"mag":6.7,"place":"5 km SE of Miyazaki, Japan","time":845736280790,"url":"https://earthquake.usgs.gov/earthquakes/eventpage/usp0007rp0"},{"lon":131.09,"lat":30.57,"depth":10,"mag":6.6,"place":"20 km SSE of Nishinoomote, Japan","time":845635820860,"url":"https://earthquake.usgs.gov/earthquakes/eventpage/usp0007rku"},{"lon":125.94,"lat":5.7,"depth":117,"mag":6,"place":"41 km SE of Caburan, Philippines","time":845568925750,"url":"https://earthquake.usgs.gov/earthquakes/eventpage/usp0007rjs"},{"lon":155.57,"lat":-7.13,"depth":24,"mag":6.8,"place":"90 km S of Panguna, Papua New Guinea","time":845335580010,"url":"https://earthquake.usgs.gov/earthquakes/eventpage/usp0007rdr"},{"lon":155.47,"lat":-7.25,"depth":33,"mag":6.1,"place":"103 km S of Panguna, Papua New Guinea","time":845134561270,"url":"https://earthquake.usgs.gov/earthquakes/eventpage/usp0007rap"},{"lon":97.94,"lat":3.44,"depth":33,"mag":6.3,"place":"62 km WSW of Binjai, Indonesia","time":844960864700,"url":"https://earthquake.usgs.gov/earthquakes/eventpage/usp0007r7z"},{"lon":32.13,"lat":34.56,"depth":33,"mag":6.8,"place":"36 km SW of Paphos, Cyprus","time":844866652130,"url":"https://earthquake.usgs.gov/earthquakes/eventpage/usp0007r4u"},{"lon":96.03,"lat":-45.78,"depth":10,"mag":6.1,"place":"southeast Indian Ridge","time":844738613930,"url":"https://earthquake.usgs.gov/earthquakes/eventpage/usp0007r2w"},{"lon":-127.88,"lat":49.05,"depth":10,"mag":6.2,"place":"144 km W of Tofino, Canada","time":844632789180,"url":"https://earthquake.usgs.gov/earthquakes/eventpage/usp0007r0w"},{"lon":151.17,"lat":45.13,"depth":33,"mag":6,"place":"258 km E of Kuril’sk, Russia","time":844255488420,"url":"https://earthquake.usgs.gov/earthquakes/eventpage/usp0007quu"},{"lon":125.48,"lat":11.76,"depth":33,"mag":6.4,"place":"3 km ENE of San Julian, Philippines","time":844249681560,"url":"https://earthquake.usgs.gov/earthquakes/eventpage/usp0007qun"},{"lon":58.07,"lat":12.43,"depth":10,"mag":6.4,"place":"Owen Fracture Zone region","time":844185023660,"url":"https://earthquake.usgs.gov/earthquakes/eventpage/usp0007qtj"},{"lon":125.37,"lat":10.04,"depth":235,"mag":6.3,"place":"22 km E of San Francisco, Philippines","time":843919842450,"url":"https://earthquake.usgs.gov/earthquakes/eventpage/usp0007qmz"},{"lon":126.54,"lat":9.45,"depth":33,"mag":6.1,"place":"42 km ENE of Cortes, Philippines","time":843222282120,"url":"https://earthquake.usgs.gov/earthquakes/eventpage/usp0007q5m"},{"lon":126.33,"lat":9.45,"depth":33,"mag":6.6,"place":"24 km NE of Cortes, Philippines","time":843192664550,"url":"https://earthquake.usgs.gov/earthquakes/eventpage/usp0007q51"},{"lon":126.28,"lat":9.46,"depth":33,"mag":6.6,"place":"22 km NNE of Cortes, Philippines","time":843192627680,"url":"https://earthquake.usgs.gov/earthquakes/eventpage/usp0007q50"},{"lon":126.29,"lat":9.6,"depth":33,"mag":6.4,"place":"26 km SE of Union, Philippines","time":843177798370,"url":"https://earthquake.usgs.gov/earthquakes/eventpage/usp0007q4r"},{"lon":165.99,"lat":-10.88,"depth":73,"mag":6.4,"place":"27 km SE of Lata, Solomon Islands","time":842706653970,"url":"https://earthquake.usgs.gov/earthquakes/eventpage/usp0007pxx"},{"lon":140.94,"lat":35.54,"depth":55,"mag":6.2,"place":"23 km SSE of Hasaki, Japan","time":842409434990,"url":"https://earthquake.usgs.gov/earthquakes/eventpage/usp0007pte"},{"lon":-71.56,"lat":-31.9,"depth":39,"mag":6,"place":"47 km SW of Illapel, Chile","time":842228439120,"url":"https://earthquake.usgs.gov/earthquakes/eventpage/usp0007pq2"},{"lon":155.89,"lat":-7.31,"depth":33,"mag":6.2,"place":"118 km SSE of Panguna, Papua New Guinea","time":842029426820,"url":"https://earthquake.usgs.gov/earthquakes/eventpage/usp0007pj1"},{"lon":121.5,"lat":21.9,"depth":20,"mag":6.8,"place":"78 km E of Hengchun, Taiwan","time":841966926150,"url":"https://earthquake.usgs.gov/earthquakes/eventpage/usp0007pfw"},{"lon":17.94,"lat":42.8,"depth":10,"mag":6,"place":"9 km ESE of Podgora, Croatia","time":841956249290,"url":"https://earthquake.usgs.gov/earthquakes/eventpage/usp0007pfj"},{"lon":-113.08,"lat":-22.06,"depth":10,"mag":6.2,"place":"Easter Island region","time":841916819420,"url":"https://earthquake.usgs.gov/earthquakes/eventpage/usp0007pez"},{"lon":-113.44,"lat":-22.12,"depth":10,"mag":6.9,"place":"Easter Island region","time":841911254480,"url":"https://earthquake.usgs.gov/earthquakes/eventpage/usp0007pet"},{"lon":-84.27,"lat":9.37,"depth":33,"mag":6.2,"place":"13 km WSW of Quepos, Costa Rica","time":841864009810,"url":"https://earthquake.usgs.gov/earthquakes/eventpage/usp0007pe6"},{"lon":78.49,"lat":-36.88,"depth":10,"mag":6,"place":"Mid-Indian Ridge","time":841143049420,"url":"https://earthquake.usgs.gov/earthquakes/eventpage/usp0007p41"},{"lon":123.28,"lat":-7.12,"depth":596,"mag":6,"place":"202 km NE of Maumere, Indonesia","time":840692142060,"url":"https://earthquake.usgs.gov/earthquakes/eventpage/usp0007nwu"},{"lon":80.42,"lat":-41.52,"depth":10,"mag":6.1,"place":"Mid-Indian Ridge","time":840435851020,"url":"https://earthquake.usgs.gov/earthquakes/eventpage/usp0007nsn"},{"lon":-178.37,"lat":51.45,"depth":33,"mag":6,"place":"Andreanof Islands, Aleutian Islands, Alaska","time":840428356180,"url":"https://earthquake.usgs.gov/earthquakes/eventpage/usp0007nsh"},{"lon":166.84,"lat":-13.3,"depth":33,"mag":6.2,"place":"99 km NW of Sola, Vanuatu","time":840094430590,"url":"https://earthquake.usgs.gov/earthquakes/eventpage/usp0007nkx"},{"lon":125.09,"lat":-0.27,"depth":42,"mag":6,"place":"174 km S of Tondano, Indonesia","time":839869227900,"url":"https://earthquake.usgs.gov/earthquakes/eventpage/usp0007nfm"},{"lon":166.69,"lat":-13.4,"depth":100,"mag":6.1,"place":"107 km WNW of Sola, Vanuatu","time":839727076780,"url":"https://earthquake.usgs.gov/earthquakes/eventpage/usp0007ndd"},{"lon":140.53,"lat":38.91,"depth":10,"mag":6,"place":"25 km NE of Shinj?, Japan","time":839700737350,"url":"https://earthquake.usgs.gov/earthquakes/eventpage/usp0007nc7"},{"lon":152.13,"lat":-4.94,"depth":33,"mag":6.2,"place":"67 km SSW of Kokopo, Papua New Guinea","time":839676019720,"url":"https://earthquake.usgs.gov/earthquakes/eventpage/usp0007nbs"},{"lon":-178.31,"lat":-20.69,"depth":550,"mag":7.4,"place":"Fiji region","time":839284702090,"url":"https://earthquake.usgs.gov/earthquakes/eventpage/usp0007n5m"},{"lon":-81,"lat":-2,"depth":33,"mag":6.3,"place":"24 km NNW of Salinas, Ecuador","time":839281156250,"url":"https://earthquake.usgs.gov/earthquakes/eventpage/usp0007n5h"},{"lon":-173.13,"lat":-15.27,"depth":41,"mag":6.7,"place":"104 km NE of Hihifo, Tonga","time":839210938250,"url":"https://earthquake.usgs.gov/earthquakes/eventpage/usp0007n46"},{"lon":161.44,"lat":-10.77,"depth":33,"mag":6.9,"place":"62 km WSW of Kirakira, Solomon Islands","time":838990529300,"url":"https://earthquake.usgs.gov/earthquakes/eventpage/usp0007n0p"},{"lon":119.95,"lat":14.51,"depth":33,"mag":6.1,"place":"38 km WSW of Sabang, Philippines","time":838748310710,"url":"https://earthquake.usgs.gov/earthquakes/eventpage/usp0007mvm"},{"lon":120.2,"lat":1.01,"depth":33,"mag":6,"place":"214 km N of Palu, Indonesia","time":838550443650,"url":"https://earthquake.usgs.gov/earthquakes/eventpage/usp0007mrs"},{"lon":-113.54,"lat":-50.15,"depth":10,"mag":6.1,"place":"southern East Pacific Rise","time":838298977080,"url":"https://earthquake.usgs.gov/earthquakes/eventpage/usp0007mkk"},{"lon":-177.25,"lat":-26.77,"depth":33,"mag":6.2,"place":"south of the Fiji Islands","time":838099204280,"url":"https://earthquake.usgs.gov/earthquakes/eventpage/usp0007mfh"},{"lon":-177.2,"lat":-26.75,"depth":33,"mag":6.5,"place":"south of the Fiji Islands","time":838092732680,"url":"https://earthquake.usgs.gov/earthquakes/eventpage/usp0007mfa"},{"lon":120.45,"lat":1,"depth":33,"mag":7,"place":"220 km NNE of Palu, Indonesia","time":838045175770,"url":"https://earthquake.usgs.gov/earthquakes/eventpage/usp0007me1"},{"lon":27.1,"lat":36.15,"depth":33,"mag":6.2,"place":"Dodecanese Islands, Greece","time":837820841880,"url":"https://earthquake.usgs.gov/earthquakes/eventpage/usp0007m9a"},{"lon":120.25,"lat":1.02,"depth":33,"mag":6.6,"place":"217 km NNE of Palu, Indonesia","time":837511656650,"url":"https://earthquake.usgs.gov/earthquakes/eventpage/usp0007m42"},{"lon":165,"lat":56.08,"depth":33,"mag":6.5,"place":"157 km E of Ust’-Kamchatsk Staryy, Russia","time":837488908340,"url":"https://earthquake.usgs.gov/earthquakes/eventpage/usp0007m3h"},{"lon":-100.97,"lat":17.6,"depth":18,"mag":6.8,"place":"26 km NNE of Coyuquilla Norte, Mexico","time":837465814080,"url":"https://earthquake.usgs.gov/earthquakes/eventpage/usp0007m35"},{"lon":145.63,"lat":18.73,"depth":177,"mag":6.3,"place":"Pagan region, Northern Mariana Islands","time":837449482070,"url":"https://earthquake.usgs.gov/earthquakes/eventpage/usp0007m2z"},{"lon":142.83,"lat":21.97,"depth":241,"mag":6.2,"place":"Mariana Islands region","time":836688988720,"url":"https://earthquake.usgs.gov/earthquakes/eventpage/usp0007ksz"},{"lon":159.81,"lat":51.73,"depth":33,"mag":6.1,"place":"164 km SE of Vilyuchinsk, Russia","time":836134355840,"url":"https://earthquake.usgs.gov/earthquakes/eventpage/usp0007kgv"},{"lon":139.75,"lat":27.73,"depth":469,"mag":6.3,"place":"Bonin Islands, Japan region","time":835759323140,"url":"https://earthquake.usgs.gov/earthquakes/eventpage/usp0007k9q"},{"lon":159.24,"lat":51.4,"depth":33,"mag":6.2,"place":"179 km SSE of Vilyuchinsk, Russia","time":835455007500,"url":"https://earthquake.usgs.gov/earthquakes/eventpage/usp0007k44"},{"lon":8.8,"lat":-53.77,"depth":10,"mag":6.4,"place":"Bouvet Island region","time":835403533470,"url":"https://earthquake.usgs.gov/earthquakes/eventpage/usp0007k3j"},{"lon":159.12,"lat":51.57,"depth":20,"mag":6.7,"place":"159 km SSE of Vilyuchinsk, Russia","time":835365430020,"url":"https://earthquake.usgs.gov/earthquakes/eventpage/usp0007k2n"},{"lon":178.12,"lat":-16.07,"depth":33,"mag":6,"place":"139 km WNW of Labasa, Fiji","time":835106134210,"url":"https://earthquake.usgs.gov/earthquakes/eventpage/usp0007jxz"},{"lon":122.59,"lat":-7.14,"depth":587,"mag":7.9,"place":"169 km NNE of Maumere, Indonesia","time":835010538540,"url":"https://earthquake.usgs.gov/earthquakes/eventpage/usp0007jw8"},{"lon":125.06,"lat":12.81,"depth":29,"mag":6.1,"place":"16 km N of Cabodiongan, Philippines","time":834764680740,"url":"https://earthquake.usgs.gov/earthquakes/eventpage/usp0007jrm"},{"lon":125.15,"lat":12.61,"depth":33,"mag":7.1,"place":"8 km NNE of Palapag, Philippines","time":834517375730,"url":"https://earthquake.usgs.gov/earthquakes/eventpage/usp0007jkw"},{"lon":-176.85,"lat":51.48,"depth":26,"mag":7.3,"place":"46 km SSW of Adak, Alaska","time":834420296000,"url":"https://earthquake.usgs.gov/earthquakes/eventpage/usp0007jfz"},{"lon":-177.63,"lat":51.56,"depth":33,"mag":7.9,"place":"77 km WSW of Adak, Alaska","time":834379415480,"url":"https://earthquake.usgs.gov/earthquakes/eventpage/usp0007jcu"},{"lon":167.13,"lat":-13.48,"depth":200,"mag":6.7,"place":"63 km NW of Sola, Vanuatu","time":834368686970,"url":"https://earthquake.usgs.gov/earthquakes/eventpage/usp0007jck"},{"lon":145.46,"lat":17.44,"depth":149,"mag":6.5,"place":"248 km N of Saipan, Northern Mariana Islands","time":834282736760,"url":"https://earthquake.usgs.gov/earthquakes/eventpage/usp0007jbe"},{"lon":-178.13,"lat":51.49,"depth":33,"mag":6.5,"place":"111 km WSW of Adak, Alaska","time":834275955170,"url":"https://earthquake.usgs.gov/earthquakes/eventpage/usp0007jbb"},{"lon":80.67,"lat":-41.33,"depth":20,"mag":6.3,"place":"Mid-Indian Ridge","time":834082538190,"url":"https://earthquake.usgs.gov/earthquakes/eventpage/usp0007j86"},{"lon":157.24,"lat":-9.32,"depth":10,"mag":6,"place":"Solomon Islands","time":833799010720,"url":"https://earthquake.usgs.gov/earthquakes/eventpage/usp0007j3n"},{"lon":157.2,"lat":-9.27,"depth":33,"mag":6.1,"place":"134 km SSE of Gizo, Solomon Islands","time":833798760500,"url":"https://earthquake.usgs.gov/earthquakes/eventpage/usp0007j3m"},{"lon":157.17,"lat":-9.31,"depth":33,"mag":6,"place":"Solomon Islands","time":833789739550,"url":"https://earthquake.usgs.gov/earthquakes/eventpage/usp0007j3e"},{"lon":-42.25,"lat":10.8,"depth":10,"mag":7,"place":"northern Mid-Atlantic Ridge","time":833683929550,"url":"https://earthquake.usgs.gov/earthquakes/eventpage/usp0007j1e"},{"lon":-26.31,"lat":-56.72,"depth":84,"mag":6,"place":"South Sandwich Islands region","time":833425477620,"url":"https://earthquake.usgs.gov/earthquakes/eventpage/usp0007hxz"},{"lon":171.47,"lat":-22.19,"depth":108,"mag":6.2,"place":"southeast of the Loyalty Islands","time":833075024590,"url":"https://earthquake.usgs.gov/earthquakes/eventpage/usp0007ht2"},{"lon":155.04,"lat":-6.61,"depth":33,"mag":6.3,"place":"58 km WSW of Panguna, Papua New Guinea","time":831822225060,"url":"https://earthquake.usgs.gov/earthquakes/eventpage/usp0007h8k"},{"lon":147.61,"lat":43.71,"depth":54,"mag":6.2,"place":"72 km E of Shikotan, Russia","time":831511200680,"url":"https://earthquake.usgs.gov/earthquakes/eventpage/usp0007h34"},{"lon":126.56,"lat":1.62,"depth":33,"mag":6,"place":"129 km NW of Ternate, Indonesia","time":831458676610,"url":"https://earthquake.usgs.gov/earthquakes/eventpage/usp0007h28"},{"lon":109.66,"lat":40.77,"depth":26,"mag":6,"place":"36 km NW of Baotou, China","time":831094367110,"url":"https://earthquake.usgs.gov/earthquakes/eventpage/usp0007gwu"},{"lon":154.83,"lat":-4.55,"depth":500,"mag":6.6,"place":"202 km NNW of Arawa, Papua New Guinea","time":831044068990,"url":"https://earthquake.usgs.gov/earthquakes/eventpage/usp0007gvt"},{"lon":154.58,"lat":-6.44,"depth":33,"mag":6,"place":"101 km W of Panguna, Papua New Guinea","time":831004355250,"url":"https://earthquake.usgs.gov/earthquakes/eventpage/usp0007guy"},{"lon":154.9,"lat":-6.74,"depth":33,"mag":6.1,"place":"80 km SW of Panguna, Papua New Guinea","time":830945109700,"url":"https://earthquake.usgs.gov/earthquakes/eventpage/usp0007gt3"},{"lon":154.85,"lat":-6.66,"depth":33,"mag":6.1,"place":"79 km WSW of Panguna, Papua New Guinea","time":830942484230,"url":"https://earthquake.usgs.gov/earthquakes/eventpage/usp0007gt0"},{"lon":155,"lat":-6.52,"depth":44,"mag":7.2,"place":"58 km WSW of Panguna, Papua New Guinea","time":830788841090,"url":"https://earthquake.usgs.gov/earthquakes/eventpage/usp0007gqq"},{"lon":-79.34,"lat":2.37,"depth":10,"mag":6.2,"place":"84 km WNW of Salahonda, Colombia","time":830594441850,"url":"https://earthquake.usgs.gov/earthquakes/eventpage/usp0007gns"},{"lon":-70.09,"lat":-23.94,"depth":50,"mag":6.6,"place":"44 km SE of Antofagasta, Chile","time":829873171190,"url":"https://earthquake.usgs.gov/earthquakes/eventpage/usp0007gbg"},{"lon":-177.04,"lat":-24.06,"depth":111,"mag":7.2,"place":"south of the Fiji Islands","time":829614654670,"url":"https://earthquake.usgs.gov/earthquakes/eventpage/usp0007g84"},{"lon":165.64,"lat":-11.18,"depth":33,"mag":6,"place":"52 km SSW of Lata, Solomon Islands","time":828315703120,"url":"https://earthquake.usgs.gov/earthquakes/eventpage/usp0007fkc"},{"lon":-168.73,"lat":52.21,"depth":33,"mag":6.3,"place":"81 km S of Nikolski, Alaska","time":828191117430,"url":"https://earthquake.usgs.gov/earthquakes/eventpage/usp0007fgz"},{"lon":-125.67,"lat":-55.85,"depth":10,"mag":6.1,"place":"southern East Pacific Rise","time":828179819410,"url":"https://earthquake.usgs.gov/earthquakes/eventpage/usp0007fgw"},{"lon":-78.74,"lat":-1.04,"depth":33,"mag":6,"place":"9 km SSW of Pujilí, Ecuador","time":828054229810,"url":"https://earthquake.usgs.gov/earthquakes/eventpage/usp0007feq"},{"lon":57.8,"lat":11.92,"depth":10,"mag":6.1,"place":"Owen Fracture Zone region","time":827998108120,"url":"https://earthquake.usgs.gov/earthquakes/eventpage/usp0007fda"},{"lon":-87.94,"lat":11.78,"depth":33,"mag":6,"place":"113 km SW of Corinto, Nicaragua","time":827959926690,"url":"https://earthquake.usgs.gov/earthquakes/eventpage/usp0007fcs"},{"lon":146.01,"lat":-55.42,"depth":10,"mag":6.1,"place":"west of Macquarie Island","time":827705942690,"url":"https://earthquake.usgs.gov/earthquakes/eventpage/usp0007f8b"},{"lon":178.69,"lat":51.22,"depth":20,"mag":6.8,"place":"Rat Islands, Aleutian Islands, Alaska","time":827465060010,"url":"https://earthquake.usgs.gov/earthquakes/eventpage/usp0007f34"},{"lon":76.7,"lat":39.99,"depth":28,"mag":6.3,"place":"83 km NE of Kashgar, China","time":827247626090,"url":"https://earthquake.usgs.gov/earthquakes/eventpage/usp0007ezd"},{"lon":147.9,"lat":-6.27,"depth":33,"mag":6.1,"place":"32 km NNE of Finschhafen, Papua New Guinea","time":827085500360,"url":"https://earthquake.usgs.gov/earthquakes/eventpage/usp0007exa"},{"lon":167.3,"lat":-14.71,"depth":164,"mag":6.7,"place":"44 km NNE of Port-Olry, Vanuatu","time":827074136710,"url":"https://earthquake.usgs.gov/earthquakes/eventpage/usp0007ex5"},{"lon":138.94,"lat":28.98,"depth":477,"mag":6.7,"place":"Bonin Islands, Japan region","time":827013846240,"url":"https://earthquake.usgs.gov/earthquakes/eventpage/usp0007evx"},{"lon":148.01,"lat":43.42,"depth":33,"mag":6.1,"place":"111 km ESE of Shikotan, Russia","time":826388136240,"url":"https://earthquake.usgs.gov/earthquakes/eventpage/usp0007eh7"},{"lon":122.22,"lat":24.09,"depth":30,"mag":6.3,"place":"63 km ENE of Hualien City, Taiwan","time":826037548680,"url":"https://earthquake.usgs.gov/earthquakes/eventpage/usp0007ec9"},{"lon":-86.77,"lat":11.9,"depth":33,"mag":6.7,"place":"30 km WSW of Villa El Carmen, Nicaragua","time":825871051520,"url":"https://earthquake.usgs.gov/earthquakes/eventpage/usp0007e9s"},{"lon":-86.86,"lat":11.66,"depth":33,"mag":6.6,"place":"39 km WSW of Masachapa, Nicaragua","time":825864911860,"url":"https://earthquake.usgs.gov/earthquakes/eventpage/usp0007e9k"},{"lon":146.56,"lat":-5.97,"depth":59,"mag":6.1,"place":"84 km ENE of Kainantu, Papua New Guinea","time":825731404520,"url":"https://earthquake.usgs.gov/earthquakes/eventpage/usp0007e7p"},{"lon":126.05,"lat":1.76,"depth":116,"mag":6.4,"place":"123 km ENE of Laikit, Laikit II (Dimembe), Indonesia","time":825500650920,"url":"https://earthquake.usgs.gov/earthquakes/eventpage/usp0007e36"},{"lon":-97.93,"lat":16.12,"depth":12,"mag":6.2,"place":"7 km SE of Santa María Chico Ometepec, Mexico","time":825239877040,"url":"https://earthquake.usgs.gov/earthquakes/eventpage/usp0007dw5"},{"lon":-98.07,"lat":15.98,"depth":21,"mag":7.1,"place":"24 km SSW of Santa María Chico Ometepec, Mexico","time":825217695870,"url":"https://earthquake.usgs.gov/earthquakes/eventpage/usp0007dv6"},{"lon":137.35,"lat":-0.87,"depth":33,"mag":6.2,"place":"144 km ENE of Biak, Indonesia","time":825177179100,"url":"https://earthquake.usgs.gov/earthquakes/eventpage/usp0007du0"},{"lon":148.54,"lat":45.26,"depth":124,"mag":6.3,"place":"52 km E of Kuril’sk, Russia","time":825001148980,"url":"https://earthquake.usgs.gov/earthquakes/eventpage/usp0007dq2"},{"lon":-71.67,"lat":-33.67,"depth":43,"mag":6,"place":"10 km SW of San Antonio, Chile","time":824996453470,"url":"https://earthquake.usgs.gov/earthquakes/eventpage/usp0007dpy"},{"lon":-79.59,"lat":-9.59,"depth":10,"mag":7.5,"place":"123 km WSW of Puerto Santa, Peru","time":824907061300,"url":"https://earthquake.usgs.gov/earthquakes/eventpage/usp0007dmb"},{"lon":-75.28,"lat":-42.13,"depth":8,"mag":6,"place":"124 km WSW of Ancud, Chile","time":824713806480,"url":"https://earthquake.usgs.gov/earthquakes/eventpage/usp0007dex"},{"lon":-14.27,"lat":-1.27,"depth":10,"mag":6.6,"place":"north of Ascension Island","time":824687368160,"url":"https://earthquake.usgs.gov/earthquakes/eventpage/usp0007dds"},{"lon":136.46,"lat":-1.34,"depth":10,"mag":6.4,"place":"46 km ESE of Biak, Indonesia","time":824610333350,"url":"https://earthquake.usgs.gov/earthquakes/eventpage/usp0007d8z"},{"lon":136.22,"lat":-0.92,"depth":32,"mag":6.5,"place":"32 km NNE of Biak, Indonesia","time":824588287020,"url":"https://earthquake.usgs.gov/earthquakes/eventpage/usp0007d78"},{"lon":135.84,"lat":-0.57,"depth":19,"mag":6.5,"place":"67 km NNW of Insrom, Indonesia","time":824566882350,"url":"https://earthquake.usgs.gov/earthquakes/eventpage/usp0007d5f"},{"lon":136.59,"lat":-0.84,"depth":33,"mag":6,"place":"Biak region, Indonesia","time":824546530270,"url":"https://earthquake.usgs.gov/earthquakes/eventpage/usp0007d3a"},{"lon":136.95,"lat":-0.89,"depth":33,"mag":8.1,"place":"1996 Biak, Indonesia Earthquake","time":824536770550,"url":"https://earthquake.usgs.gov/earthquakes/eventpage/official19960217055930550_33"},{"lon":142.38,"lat":37.35,"depth":41,"mag":6.7,"place":"123 km E of Namie, Japan","time":824484178830,"url":"https://earthquake.usgs.gov/earthquakes/eventpage/usp0007d0t"},{"lon":-173.22,"lat":-15.28,"depth":33,"mag":6,"place":"96 km NE of Hihifo, Tonga","time":824470471110,"url":"https://earthquake.usgs.gov/earthquakes/eventpage/usp0007d0k"},{"lon":-15.28,"lat":-1.5,"depth":11,"mag":6.6,"place":"north of Ascension Island","time":824463898410,"url":"https://earthquake.usgs.gov/earthquakes/eventpage/usp0007d0f"},{"lon":118.67,"lat":-11.04,"depth":8,"mag":6.1,"place":"232 km SW of Waingapu, Indonesia","time":824116087990,"url":"https://earthquake.usgs.gov/earthquakes/eventpage/usp0007ct1"},{"lon":146.63,"lat":-6,"depth":69,"mag":6.1,"place":"89 km NNW of Lae, Papua New Guinea","time":823887234290,"url":"https://earthquake.usgs.gov/earthquakes/eventpage/usp0007cnm"},{"lon":149.48,"lat":44.12,"depth":33,"mag":6,"place":"176 km SE of Kuril’sk, Russia","time":823733620050,"url":"https://earthquake.usgs.gov/earthquakes/eventpage/usp0007chp"},{"lon":149.89,"lat":45.32,"depth":43,"mag":7.2,"place":"158 km E of Kuril’sk, Russia","time":823729006300,"url":"https://earthquake.usgs.gov/earthquakes/eventpage/usp0007chh"},{"lon":120.19,"lat":1.02,"depth":14,"mag":6.1,"place":"216 km N of Palu, Indonesia","time":823679838110,"url":"https://earthquake.usgs.gov/earthquakes/eventpage/usp0007cgh"},{"lon":100.28,"lat":27.29,"depth":11,"mag":6.6,"place":"47 km N of Lijiang, China","time":823346060120,"url":"https://earthquake.usgs.gov/earthquakes/eventpage/usp0007c7g"},{"lon":146.27,"lat":44.85,"depth":170,"mag":6.2,"place":"93 km NNE of Otrada, Russia","time":823159084230,"url":"https://earthquake.usgs.gov/earthquakes/eventpage/usp0007c3b"},{"lon":149.37,"lat":44.47,"depth":21,"mag":6,"place":"145 km SE of Kuril’sk, Russia","time":823120242370,"url":"https://earthquake.usgs.gov/earthquakes/eventpage/usp0007c29"},{"lon":-178.3,"lat":-32.92,"depth":33,"mag":6.4,"place":"south of the Kermadec Islands","time":823040997150,"url":"https://earthquake.usgs.gov/earthquakes/eventpage/usp0007c0u"},{"lon":-178.25,"lat":-32.95,"depth":14,"mag":6.1,"place":"south of the Kermadec Islands","time":823039209580,"url":"https://earthquake.usgs.gov/earthquakes/eventpage/usp0007c0r"},{"lon":126.42,"lat":9.19,"depth":33,"mag":6,"place":"26 km E of Tigao, Philippines","time":822764889380,"url":"https://earthquake.usgs.gov/earthquakes/eventpage/usp0007bun"},{"lon":-25.9,"lat":-60.61,"depth":10,"mag":6.2,"place":"South Sandwich Islands region","time":822352797450,"url":"https://earthquake.usgs.gov/earthquakes/eventpage/usp0007bjd"},{"lon":140.07,"lat":-4.4,"depth":109,"mag":6.1,"place":"208 km SSW of Abepura, Indonesia","time":821873206710,"url":"https://earthquake.usgs.gov/earthquakes/eventpage/usp0007b87"},{"lon":159.59,"lat":53.83,"depth":33,"mag":6.6,"place":"106 km NE of Yelizovo, Russia","time":820490271400,"url":"https://earthquake.usgs.gov/earthquakes/eventpage/usp0007a08"},{"lon":119.93,"lat":0.73,"depth":24,"mag":7.9,"place":"181 km N of Palu, Indonesia","time":820483510830,"url":"https://earthquake.usgs.gov/earthquakes/eventpage/usp00079zv"},{"lon":-174.23,"lat":-20.39,"depth":33,"mag":6,"place":"65 km S of Pangai, Tonga","time":820460056000,"url":"https://earthquake.usgs.gov/earthquakes/eventpage/usp00079z4"}]}