{"AFG":8.73,"ALB":0,"DZA":0,"ASM":0,"AGO":0,"ATG":0,"ARG":1.38,"ARM":0,"ABW":0,"AUS":61.463,"AUT":2.623,"AZE":0,"BHS":0,"BHR":0,"BGD":1.402,"BRB":0,"BLR":0.087,"BEL":0,"BLZ":0,"BEN":0,"BMU":0,"BTN":0,"BOL":0,"BIH":75.985,"BWA":99.669,"BRA":3.877,"VGB":0,"BRN":0,"BGR":46.655,"BFA":0,"BDI":0,"KHM":53.846,"CMR":0,"CAN":9.384,"CPV":0,"CYM":0,"CAF":0,"TCD":0,"CHL":37.121,"CHN":67.077,"COL":4.014,"COM":0,"COG":0,"COK":0,"CRI":0,"CIV":0,"HRV":11.64,"CUB":0,"CYP":0,"CZE":48.321,"COD":0,"DNK":20.097,"DJI":0,"DMA":0,"DOM":12.552,"TLS":0,"ECU":0,"EGY":0,"GNQ":0,"ERI":0,"EST":0.152,"SWZ":4.651,"ETH":0,"FLK":0,"FRO":0,"FJI":0,"FIN":8.679,"FRA":2.305,"PYF":0,"GAB":0,"GMB":0,"GEO":0.175,"DEU":37.436,"GHA":0,"GIB":0,"GRC":34.234,"GRL":0,"GRD":0,"GLP":27.841,"GUM":0,"GTM":27.796,"GIN":0,"GNB":0,"GUY":0,"HTI":0,"HND":0,"HKG":64.808,"HUN":14.976,"ISL":0,"IND":76.261,"IDN":55.66,"IRN":0.226,"IRQ":0,"IRL":11.822,"ISR":32.666,"ITA":11.171,"JAM":0,"JPN":33.753,"JOR":0,"KAZ":68.396,"KEN":0,"KIR":0,"KWT":0,"KGZ":7.547,"LAO":35.179,"LVA":0,"LBN":0,"LSO":0,"LBR":0,"LBY":0,"LTU":0,"LUX":0,"MAC":0,"MDG":6.061,"MWI":0,"MYS":42.872,"MDV":0,"MLI":0,"MLT":0,"MRT":0,"MUS":42.122,"MEX":9.377,"MDA":0,"MNG":91.211,"MNE":54.839,"MSR":0,"MAR":54.947,"MOZ":0,"MMR":6.702,"NAM":3.955,"NRU":0,"NPL":0,"NLD":27.042,"NCL":41.486,"NZL":1.328,"NIC":0,"NER":37.5,"NGA":0,"PRK":46.18,"MKD":60.536,"NOR":0.027,"OMN":0,"PAK":8.369,"PSE":0,"PAN":1.54,"PNG":0,"PRY":0,"PER":1.442,"PHL":49.65,"POL":77.194,"PRT":25.473,"PRI":14.164,"QAT":0,"REU":38.255,"ROU":26.409,"RUS":15.947,"RWA":3.077,"SHN":0,"KNA":0,"LCA":0,"SPM":0,"VCT":0,"WSM":0,"STP":0,"SAU":0,"SEN":6.568,"SRB":72.613,"SYC":0,"SLE":0,"SGP":1.301,"SVK":10.904,"SVN":30.031,"SLB":0,"SOM":0,"ZAF":89.637,"KOR":45.244,"SSD":0,"ESP":16.569,"LKA":34.385,"SDN":0,"SUR":0,"SWE":0.195,"CHE":0,"SYR":0,"TWN":48.365,"TJK":5.411,"TZA":0,"THA":20.217,"TGO":0,"TON":0,"TTO":0,"TUN":0,"TUR":32.79,"TKM":0,"TCA":0,"UGA":0,"UKR":31.614,"ARE":0,"GBR":6.661,"USA":29.757,"VIR":0,"URY":0,"UZB":3.435,"VUT":0,"VEN":0,"VNM":34.773,"YEM":0,"ZMB":8.791,"ZWE":44.768}