{"AFG":310,"AGO":1091,"AIA":802,"ALB":1241,"AND":973,"ARE":55,"ARG":664,"ARM":837,"ASM":2507,"ATG":768,"AUS":472,"AUT":1386,"AZE":587,"BDI":1995,"BEL":928,"BEN":1029,"BFA":662,"BGD":2225,"BGR":714,"BHR":63,"BHS":924,"BIH":1149,"BLR":756,"BLZ":1397,"BOL":1415,"BRA":1657,"BRN":3213,"BTN":3399,"BWA":406,"CAF":1147,"CAN":728,"CHE":1668,"CHL":1359,"CHN":873,"CIV":1197,"CMR":1702,"COD":1495,"COG":1448,"COK":1829,"COL":3044,"COM":1419,"CPV":163,"CRI":3153,"CUB":923,"CYM":943,"CYP":340,"CZE":833,"DEU":910,"DJI":201,"DNK":851,"DOM":920,"DZA":48,"ECU":3328,"EGY":12,"ERI":339,"ESP":640,"EST":796,"ETH":1078,"FIN":808,"FJI":2657,"FRA":1134,"FRO":1057,"GAB":2031,"GBR":1054,"GEO":1260,"GHA":1072,"GIN":1708,"GMB":687,"GNB":1401,"GNQ":2927,"GRC":724,"GRL":508,"GTM":1656,"GUY":2055,"HKG":1937,"HMD":1420,"HND":1580,"HRV":1066,"HTI":832,"HUN":717,"IDN":3620,"IMN":1147,"IND":1275,"IRL":1143,"IRN":263,"IRQ":212,"ISL":1463,"ISR":216,"ITA":1032,"JAM":949,"JOR":82,"JPN":1927,"KAZ":349,"KEN":821,"KGZ":961,"KHM":1869,"KIR":1298,"KOR":1321,"KWT":124,"LAO":1888,"LBN":558,"LBR":2305,"LBY":19,"LKA":1869,"LSO":967,"LTU":778,"LUX":923,"LVA":774,"MAR":212,"MDA":550,"MDG":1475,"MEX":751,"MKD":758,"MLI":256,"MMR":2339,"MNE":1525,"MNG":279,"MOZ":905,"MRT":65,"MUS":1162,"MWI":1446,"MYS":3180,"NAM":271,"NCL":1621,"NER":123,"NGA":1097,"NIC":1768,"NLD":886,"NOR":1306,"NPL":2230,"NZL":1567,"OMN":62,"PAK":447,"PAN":3116,"PER":2165,"PHL":2850,"PNG":4639,"POL":788,"PRI":1027,"PRK":1260,"PRT":717,"PRY":1173,"PSE":332,"PYF":1721,"QAT":61,"ROU":770,"RUS":618,"RWA":1606,"SAU":57,"SDN":221,"SEN":470,"SLB":4423,"SLE":2600,"SLV":1359,"SOM":339,"SRB":787,"SSD":877,"STP":1509,"SUR":2089,"SVK":873,"SVN":1452,"SWE":817,"SWZ":816,"SYC":2065,"SYR":206,"TCD":309,"TGO":1245,"THA":1631,"TJK":715,"TKM":160,"TLS":1810,"TTO":1250,"TUN":154,"TUR":674,"TZA":1167,"UGA":1526,"UKR":628,"URY":1234,"USA":880,"UZB":247,"VCT":951,"VEN":1913,"VIR":879,"VNM":2139,"VUT":2435,"WSM":2793,"YEM":162,"ZAF":460,"ZMB":1112,"ZWE":750}