{"events":[{"lon":125.05,"lat":11.45,"type":"FL","level":"RED","name":"Flood in Philippines","country":"Philippines","severity":"Magnitude 5.89","from":"2013-11-08","to":"2013-11-19","eventid":4100},{"lon":107.71,"lat":15.58,"type":"FL","level":"ORANGE","name":"Flood in Vietnam","country":"Vietnam","severity":"Magnitude 5.64","from":"2013-11-14","to":"2013-11-19","eventid":4103},{"lon":130.27,"lat":50.53,"type":"FL","level":"ORANGE","name":"Flood in China","country":"China","severity":"Magnitude 8.30","from":"2013-08-07","to":"2013-10-14","eventid":4083},{"lon":105.08,"lat":12.66,"type":"FL","level":"ORANGE","name":"Flood in Cambodia","country":"Cambodia","severity":"Magnitude 6.15","from":"2013-09-27","to":"2013-10-14","eventid":4090},{"lon":84.25,"lat":21.27,"type":"FL","level":"ORANGE","name":"Flood in India","country":"India","severity":"Magnitude 6.17","from":"2013-10-12","to":"2013-10-14","eventid":4091},{"lon":101.69,"lat":13.08,"type":"FL","level":"RED","name":"Flood in Thailand","country":"Thailand","severity":"Magnitude 6.85","from":"2013-09-30","to":"2013-10-14","eventid":4092},{"lon":120.57,"lat":29.15,"type":"FL","level":"ORANGE","name":"Flood in China","country":"China","severity":"Magnitude 5.64","from":"2013-10-08","to":"2013-10-14","eventid":4095},{"lon":121.14,"lat":16.32,"type":"FL","level":"ORANGE","name":"Flood in Philippines","country":"Philippines","severity":"Magnitude 5.96","from":"2013-08-13","to":"2013-08-21","eventid":4084},{"lon":28.99,"lat":13.69,"type":"FL","level":"ORANGE","name":"Flood in Sudan","country":"Sudan","severity":"Magnitude 7.50","from":"2013-08-01","to":"2013-08-21","eventid":4077},{"lon":70.64,"lat":32.81,"type":"FL","level":"ORANGE","name":"Flood in Pakistan","country":"Pakistan","severity":"Magnitude 6.76","from":"2013-08-01","to":"2013-08-07","eventid":4078},{"lon":94.92,"lat":27.39,"type":"FL","level":"RED","name":"Flood in India","country":"India","severity":"Magnitude 6.24","from":"2013-06-23","to":"2013-07-15","eventid":4069},{"lon":104.02,"lat":30.46,"type":"FL","level":"ORANGE","name":"Flood in China","country":"China","severity":"Magnitude 6.84","from":"2013-07-05","to":"2013-07-15","eventid":4071},{"lon":118.14,"lat":25.86,"type":"FL","level":"ORANGE","name":"Flood in China","country":"China","severity":"Magnitude 5.66","from":"2013-07-13","to":"2013-07-15","eventid":4072},{"lon":76.61,"lat":32.71,"type":"FL","level":"RED","name":"Flood in India","country":"India","severity":"Magnitude 6.50","from":"2013-06-12","to":"2013-06-27","eventid":4065},{"lon":-109.65,"lat":51.24,"type":"FL","level":"ORANGE","name":"Flood in Canada","country":"Canada","severity":"Magnitude 6.69","from":"2013-06-20","to":"2013-06-27","eventid":4068},{"lon":91.19,"lat":23.64,"type":"FL","level":"RED","name":"Flood in Bangladesh","country":"Bangladesh","severity":"Magnitude 5.52","from":"2013-05-14","to":"2013-05-16","eventid":4056},{"lon":80.53,"lat":7.13,"type":"FL","level":"ORANGE","name":"Flood in Sri Lanka","country":"Sri Lanka","severity":"Magnitude 4.84","from":"2013-05-13","to":"2013-05-16","eventid":4058},{"lon":32.68,"lat":-24.8,"type":"FL","level":"ORANGE","name":"Flood in Mozambique","country":"Mozambique","severity":"Magnitude 6.77","from":"2013-01-17","to":"2013-03-04","eventid":4023},{"lon":123.58,"lat":-7.79,"type":"VO","level":"Orange","name":"Eruption  Tara, Batu","country":"Lesser Sunda Is","severity":"","from":"2013-07-14","to":"2013-07-14","eventid":161},{"lon":145.04,"lat":-4.08,"type":"VO","level":"Orange","name":"Eruption  Manam","country":"New Guinea-NE of","severity":"","from":"2013-06-22","to":"2013-06-22","eventid":75},{"lon":121.71,"lat":-8.32,"type":"VO","level":"Orange","name":"Eruption  Paluweh","country":"Lesser Sunda Is","severity":"","from":"2013-06-19","to":"2013-06-19","eventid":154},{"lon":155.19,"lat":-6.14,"type":"VO","level":"Orange","name":"Eruption  Bagana","country":"Bougainville-SW Pacific","severity":"","from":"2013-06-17","to":"2013-06-17","eventid":90},{"lon":152.2,"lat":-4.27,"type":"VO","level":"Orange","name":"Eruption  Rabaul","country":"New Britain-SW Pac","severity":"","from":"2013-04-18","to":"2013-04-18","eventid":86},{"lon":124.79,"lat":1.36,"type":"VO","level":"Orange","name":"Eruption  Lokon-Empung","country":"Sulawesi-Indonesia","severity":"","from":"2013-04-11","to":"2013-04-11","eventid":171},{"lon":125.4,"lat":2.78,"type":"VO","level":"Orange","name":"Eruption  Karangetang [Api Siau]","country":"Sangihe Is-Indonesia","severity":"","from":"2013-04-09","to":"2013-04-09","eventid":175},{"lon":145.96,"lat":-4.65,"type":"VO","level":"Red","name":"Eruption  Karkar","country":"New Guinea-NE of","severity":"","from":"2013-03-16","to":"2013-03-16","eventid":76},{"lon":93.86,"lat":12.28,"type":"VO","level":"Red","name":"Eruption  Barren Island","country":"Andaman Is-Indian O","severity":"","from":"2013-02-17","to":"2013-02-17","eventid":108},{"lon":45.3,"lat":-32.3,"type":"TC","level":"Red","name":"Tropical Cyclone BEJISA-14","country":"Miscellaneous (French) Indian Ocean Islands","severity":"Tropical Storm (maximum wind speed of 204 km/h)","from":"2013-12-31","to":"2014-01-05","eventid":42161},{"lon":81.9,"lat":15,"type":"TC","level":"Orange","name":"Tropical Cyclone LEHAR-13","country":"India","severity":"Tropical Storm (maximum wind speed of 138 km/h)","from":"2013-11-24","to":"2013-11-28","eventid":41483},{"lon":81.3,"lat":16.2,"type":"TC","level":"Orange","name":"Tropical Cyclone HELEN-13","country":"India","severity":"Tropical Storm (maximum wind speed of 111 km/h)","from":"2013-11-20","to":"2013-11-22","eventid":41389},{"lon":107.2,"lat":21.8,"type":"TC","level":"Red","name":"Tropical Cyclone HAIYAN-13","country":"China, Viet Nam, Philippines, Palau","severity":"Tropical Storm (maximum wind speed of 315 km/h)","from":"2013-11-04","to":"2013-11-11","eventid":41058},{"lon":112.3,"lat":18.6,"type":"TC","level":"Orange","name":"Tropical Cyclone KROSA-13","country":"Philippines","severity":"Tropical Depression (maximum wind speed of 185 km/h)","from":"2013-10-29","to":"2013-11-04","eventid":40957},{"lon":108.2,"lat":15.9,"type":"TC","level":"Red","name":"Tropical Cyclone NARI-13","country":"Laos, Viet Nam, Philippines","severity":"Hurricane/Typhoon > 74 mph (maximum wind speed of 194 km/h)","from":"2013-10-09","to":"2013-10-15","eventid":40482},{"lon":84.9,"lat":19.6,"type":"TC","level":"Red","name":"Tropical Cyclone PHAILIN-13","country":"India","severity":"Hurricane/Typhoon > 74 mph (maximum wind speed of 259 km/h)","from":"2013-10-09","to":"2013-10-12","eventid":40489},{"lon":120.3,"lat":27.4,"type":"TC","level":"Orange","name":"Tropical Cyclone FITOW-13","country":"China, Japan","severity":"Tropical Storm (maximum wind speed of 167 km/h)","from":"2013-09-30","to":"2013-10-06","eventid":40330},{"lon":105.9,"lat":17.8,"type":"TC","level":"Orange","name":"Tropical Cyclone WUTIP-13","country":"Laos, Thailand, Viet Nam","severity":"Hurricane/Typhoon > 74 mph (maximum wind speed of 167 km/h)","from":"2013-09-27","to":"2013-09-30","eventid":40266},{"lon":115.2,"lat":22.9,"type":"TC","level":"Red","name":"Tropical Cyclone USAGI-13","country":"China","severity":"Hurricane/Typhoon > 74 mph (maximum wind speed of 259 km/h)","from":"2013-09-17","to":"2013-09-22","eventid":40084},{"lon":-107.8,"lat":25,"type":"TC","level":"Orange","name":"Tropical Cyclone MANUEL-13","country":"Mexico","severity":"Hurricane/Typhoon > 74 mph (maximum wind speed of 120 km/h)","from":"2013-09-13","to":"2013-09-19","eventid":40022},{"lon":119.6,"lat":25.6,"type":"TC","level":"Orange","name":"Tropical Cyclone TRAMI-13","country":"China","severity":"Hurricane/Typhoon > 74 mph (maximum wind speed of 138 km/h)","from":"2013-08-18","to":"2013-08-21","eventid":39519},{"lon":111.4,"lat":22,"type":"TC","level":"Red","name":"Tropical Cyclone UTOR-13","country":"China, Philippines","severity":"Hurricane/Typhoon > 74 mph (maximum wind speed of 241 km/h)","from":"2013-08-09","to":"2013-08-14","eventid":39372},{"lon":106.4,"lat":21.8,"type":"TC","level":"Orange","name":"Tropical Cyclone JEBI-13","country":"China, Viet Nam","severity":"Tropical Storm (maximum wind speed of 111 km/h)","from":"2013-07-31","to":"2013-08-03","eventid":39225},{"lon":119.1,"lat":26.8,"type":"TC","level":"Orange","name":"Tropical Cyclone SOULIK-13","country":"China, Japan","severity":"Tropical Storm (maximum wind speed of 231 km/h)","from":"2013-07-08","to":"2013-07-13","eventid":38773},{"lon":-95,"lat":18.5,"type":"TC","level":"Orange","name":"Tropical Cyclone BARBARA-13","country":"Mexico","severity":"Tropical Depression (maximum wind speed of 120 km/h)","from":"2013-05-28","to":"2013-05-30","eventid":38075},{"lon":91,"lat":23,"type":"TC","level":"Orange","name":"Tropical Cyclone MAHASEN-13","country":"Bangladesh, India","severity":"Tropical Storm (maximum wind speed of 93 km/h)","from":"2013-05-11","to":"2013-05-16","eventid":37639},{"lon":57.5,"lat":-27,"type":"TC","level":"Orange","name":"Tropical Cyclone HARUNA-13","country":"Madagascar","severity":"Tropical Storm (maximum wind speed of 185 km/h)","from":"2013-02-19","to":"2013-02-25","eventid":35803}]}