{"AFG":9.176,"ALB":2.642,"DZA":26.926,"AND":0.038,"AGO":13.385,"ATG":0.041,"ARG":87.88,"ARM":1.15,"ABW":0.013,"AUS":119.856,"AUT":12.875,"AZE":4.656,"BHS":0.083,"BHR":11.949,"BGD":51.201,"BRB":0.161,"BLR":17.984,"BEL":20.177,"BLZ":0.141,"BEN":1.612,"BTN":0.501,"BOL":14.642,"BIH":3.777,"BWA":3.629,"BRA":154.211,"VGB":0.008,"BRN":0.059,"BGR":15.305,"BFA":4.234,"BDI":1.188,"KHM":13.851,"CMR":4.074,"CAN":66.866,"CPV":0.054,"CAF":4.195,"TCD":7.434,"CHL":14.181,"CHN":462.457,"COL":39.755,"COM":0.168,"COG":1.264,"COK":0.01,"CRI":2.218,"CIV":2.738,"HRV":3.559,"CUB":14.45,"CYP":0.335,"CZE":21.401,"COD":12.772,"DNK":12.163,"DJI":0.145,"DMA":0.023,"DOM":4.047,"TLS":0.433,"ECU":5.673,"EGY":23.377,"SLV":2.776,"GNQ":0.071,"ERI":2.454,"EST":2.913,"SWZ":0.912,"ETH":38.261,"FJI":0.408,"FIN":12.364,"FRA":118.889,"GAB":0.371,"GMB":0.47,"GEO":3.151,"DEU":173.301,"GHA":3.744,"GRC":10.429,"GRD":0.034,"GTM":4.108,"GIN":4.114,"GNB":0.65,"GUY":1.261,"HTI":3.747,"HND":3.217,"HKG":1.347,"HUN":12.657,"ISL":0.51,"IND":454.7,"IDN":82.408,"IRN":64.925,"IRQ":48.385,"IRL":12.862,"ISR":26.808,"ITA":52.162,"JAM":2.315,"JPN":57.505,"JOR":0.534,"KAZ":53.643,"KEN":11.625,"KIR":0.008,"KWT":37.975,"KGZ":3.856,"LAO":3.338,"LVA":3.535,"LBN":0.822,"LSO":0.976,"LBR":0.543,"LBY":44.068,"LIE":0.012,"LTU":5.625,"LUX":0.573,"MAC":0.023,"MDG":14.086,"MWI":1.401,"MYS":6.724,"MDV":0.008,"MLI":7.632,"MLT":0.073,"MRT":4.022,"MUS":0.329,"MEX":52.496,"FSM":0.002,"MDA":3.162,"MNG":7.763,"MNE":0.877,"MAR":8.763,"MOZ":8.942,"MMR":35.99,"NAM":4.384,"NRU":0.001,"NPL":12.651,"NLD":23.921,"NZL":28.697,"NIC":3.442,"NER":6.181,"NGA":64.38,"NIU":0.001,"PRK":9.955,"MKD":2.302,"NOR":6.33,"OMN":0.153,"PAK":45.078,"PLW":0.006,"PAN":1.85,"PNG":0.756,"PRY":8.311,"PER":18.177,"PHL":43.145,"POL":110.444,"PRT":9.376,"QAT":1.746,"ROU":28.315,"RUS":355.315,"RWA":2.367,"SHN":0.002,"KNA":0.041,"LCA":0.044,"VCT":0.028,"WSM":0.071,"STP":0.017,"SAU":15.321,"SEN":4.79,"SRB":8.857,"SYC":0.016,"SLE":1.718,"SGP":0.582,"SVK":8.131,"SVN":2.973,"SLB":0.045,"SOM":11.2,"ZAF":35.778,"KOR":19.971,"SSD":11.8,"ESP":27.987,"LKA":7.049,"SDN":15.922,"SUR":0.368,"SWE":11.87,"CHE":6.781,"SYR":4.105,"TWN":8.658,"TJK":3.316,"TZA":14.751,"THA":53.552,"TGO":1.148,"TON":0.036,"TTO":2.195,"TUN":3.385,"TUR":31.184,"TKM":6.478,"TCA":0.001,"TUV":0.003,"UGA":6.379,"UKR":94.08,"ARE":0.2,"GBR":161.679,"USA":735.74,"URY":17.703,"UZB":15.157,"VUT":0.124,"VEN":91.826,"VNM":37.379,"YEM":3.153,"ZMB":8.146,"ZWE":5.462}