{"DZA":0.153,"ARG":12.678,"AUS":4.024,"AUT":26.99,"AZE":4.114,"BGD":1.051,"BLR":0.034,"BEL":1.178,"BRA":41.147,"BGR":4.738,"CAN":27.208,"CHL":21.915,"CHN":5.267,"COL":30.936,"HRV":16.644,"CYP":0.012,"CZE":1.902,"DNK":10.242,"ECU":15.435,"EGY":4.876,"EST":0.583,"FIN":17.117,"FRA":5.702,"DEU":5.797,"GRC":5.149,"HKG":0.001,"HUN":1.557,"ISL":70.76,"IND":7.134,"IDN":3.234,"IRN":2.353,"IRQ":4.466,"IRL":3.451,"ISR":0.068,"ITA":6.427,"JPN":5.011,"KAZ":3.832,"KWT":0,"LVA":16.884,"LTU":1.571,"LUX":1.321,"MYS":2.242,"MEX":5.178,"MAR":1.895,"NLD":2.24,"NZL":34.047,"MKD":13.409,"NOR":65.662,"OMN":0,"PAK":11.995,"PER":33.532,"PHL":19.318,"POL":1.203,"PRT":14.808,"QAT":0,"ROU":10.578,"RUS":5.962,"SAU":0,"SGP":0.247,"SVK":6.177,"SVN":11.735,"ZAF":0.692,"KOR":0.42,"ESP":7.933,"LKA":18.984,"SWE":31.833,"CHE":25.217,"TWN":1.411,"THA":2.724,"TTO":0.041,"TUR":10.874,"TKM":0.005,"UKR":2.136,"ARE":0,"GBR":2.047,"USA":4.502,"UZB":2.986,"VEN":23.661,"VNM":15.766}