{"DZA":0.001,"ARG":0.531,"ARM":0.24,"AUS":4.078,"AUT":1.392,"AZE":0.634,"BLR":0.522,"BEL":6.104,"BOL":0.05,"BRA":0.108,"BGR":0.193,"CAN":9.652,"CHL":1.133,"CHN":0.068,"COL":0.009,"CRI":0.134,"CUB":1.334,"CZE":4.437,"DNK":3.298,"DOM":0.09,"ECU":0.028,"EGY":0.015,"SLV":0,"EST":1.033,"FIN":0.059,"FRA":2.804,"GEO":0.156,"DEU":7.862,"GRC":0.012,"GTM":0.018,"HTI":0,"HND":0.056,"HUN":1.518,"IND":0.113,"IDN":0.149,"IRN":0.202,"ITA":0.644,"JPN":1.093,"KAZ":1.505,"KGZ":0.486,"LVA":0.35,"LTU":0.455,"MYS":0.182,"MEX":1.27,"MDA":0.65,"NLD":3.472,"NZL":4.358,"NIC":0.008,"NGA":0.003,"PRK":0.075,"NOR":3.103,"PAN":0.037,"PRY":0,"PER":0.487,"PHL":0.006,"POL":4.452,"PRT":0.501,"ROU":0.247,"RUS":0.887,"SVK":4.805,"ZAF":3.249,"KOR":0.002,"ESP":0.864,"SWE":2.789,"CHE":2.225,"TWN":0.397,"TJK":0.322,"TTO":1.107,"TUN":0.005,"TUR":0.036,"TKM":1.046,"UKR":0.773,"GBR":11.03,"USA":15.553,"URY":0.651,"UZB":0.625,"VEN":0.038,"VNM":0.097,"ZWE":0.826}