{"AFG":0.018,"ALB":0.467,"DZA":0.45,"AGO":0.086,"ATG":0.436,"ARG":2.114,"ARM":1.422,"ABW":14.804,"AUS":7.816,"AUT":4.191,"AZE":3.926,"BHS":1.365,"BHR":10.237,"BGD":0.03,"BRB":0.574,"BLR":3.794,"BEL":10.415,"BLZ":0.367,"BEN":0.053,"BMU":2.757,"BOL":0.277,"BES":26.436,"BIH":1.189,"BRA":0.548,"BRN":4.606,"BGR":1.605,"BFA":0.001,"BDI":0.003,"KHM":0.021,"CMR":0.05,"CAN":10.775,"CPV":0.112,"CAF":0.046,"TCD":0.016,"CHL":1.582,"CHN":0.316,"COL":0.887,"COG":0.145,"CRI":0.316,"CIV":0.16,"HRV":0.929,"CUB":1.036,"CUW":93.128,"CYP":0.844,"CZE":8.154,"COD":0.249,"DNK":6.101,"DJI":0.502,"DMA":0.069,"DOM":0.329,"ECU":0.299,"EGY":0.447,"SLV":0.188,"GNQ":0.148,"EST":8.936,"SWZ":0.012,"ETH":0.012,"FRO":3.078,"FJI":0.493,"FIN":2.581,"FRA":5.421,"PYF":0.595,"GAB":0.033,"GMB":0.042,"GEO":1.004,"DEU":10.283,"GHA":0.201,"GRC":0.746,"GRL":7.946,"GRD":0.131,"GTM":0.259,"GIN":0.051,"GNB":0.019,"GUY":1.067,"HTI":0.076,"HND":0.244,"HKG":0.758,"HUN":3.634,"ISL":5.783,"IND":0.203,"IDN":0.27,"IRN":0.846,"IRQ":0.644,"IRL":4.04,"ISR":3.011,"ITA":1.522,"JAM":0.634,"JPN":1.536,"JOR":0.609,"KAZ":8.601,"KEN":0.304,"KWT":9.922,"KGZ":3.033,"LAO":0.014,"LVA":3.444,"LBN":1.043,"LBR":0.058,"LBY":0.345,"LTU":4.128,"LUX":32.412,"MAC":0.112,"MDG":0.068,"MWI":0.127,"MYS":1.067,"MLT":1.071,"MUS":0.214,"MEX":1.253,"MDA":3.839,"MNG":0.695,"MNE":0.885,"MAR":0.35,"MOZ":0.219,"MMR":0.073,"NPL":0.005,"NLD":5.674,"NCL":10.117,"NZL":4.39,"NIC":0.255,"NER":0.009,"NGA":0.066,"PRK":0.706,"MKD":1.431,"NOR":3.329,"PAK":0.185,"PLW":1.303,"PAN":0.808,"PNG":0.074,"PRY":0.113,"PER":0.694,"PHL":0.289,"POL":5.694,"PRT":0.746,"QAT":14.626,"ROU":2.105,"RUS":5.68,"RWA":0.006,"KNA":0.211,"LCA":0.117,"SPM":7.659,"VCT":0.102,"WSM":0.111,"STP":0.057,"SAU":1.04,"SEN":0.1,"SRB":1.601,"SLE":0.086,"SGP":3.07,"SXM":610.668,"SVK":6.382,"SVN":1.888,"SLB":0.09,"SOM":0.026,"ZAF":5.706,"KOR":0.291,"SSD":0.028,"ESP":1.384,"LKA":0.193,"SDN":0.119,"SUR":1.383,"SWE":5.385,"CHE":2.725,"SYR":0.406,"TWN":0.791,"TJK":1.857,"TZA":0.064,"THA":0.102,"TGO":0.026,"TON":0.128,"TTO":3.672,"TUN":0.398,"TUR":0.56,"TKM":6.053,"UGA":0.04,"UKR":5.025,"GBR":11.257,"USA":16.417,"URY":1.656,"UZB":3.666,"VEN":8.844,"VNM":0.125,"YEM":0.496,"ZMB":1.511,"ZWE":1.708}