{"AFG":0.114,"ALB":1.484,"DZA":0.687,"AGO":0.293,"ATG":15.745,"ARG":2.981,"ARM":2.001,"ABW":10.739,"AUS":10.704,"AUT":5.709,"AZE":5.745,"BHS":9.569,"BHR":5.028,"BGD":0.059,"BRB":1.769,"BLR":6.753,"BEL":12.403,"BLZ":0.894,"BEN":0.052,"BMU":4.432,"BOL":0.496,"BES":18.911,"BIH":2.175,"BRA":0.851,"VGB":1.624,"BRN":3.396,"BGR":7.104,"BFA":0.019,"BDI":0.016,"KHM":0.071,"CMR":0.083,"CAN":14.626,"CPV":0.108,"CAF":0.091,"TCD":0.035,"CHL":2.228,"CHN":0.634,"COL":1.344,"COM":0.08,"COG":0.342,"CRI":0.596,"CIV":0.32,"HRV":1.973,"CUB":1.883,"CUW":64.272,"CYP":2.554,"CZE":12.984,"COD":0.177,"DNK":10.952,"DJI":0.943,"DMA":0.329,"DOM":0.565,"ECU":0.537,"EGY":0.693,"SLV":0.362,"GNQ":0.092,"EST":16.282,"SWZ":0.664,"ETH":0.065,"FRO":4.874,"FJI":0.775,"FIN":7.192,"FRA":8.431,"PYF":1.447,"GAB":3.425,"GMB":0.074,"GEO":1.694,"DEU":12.734,"GHA":0.195,"GRC":2.556,"GRL":12.67,"GRD":0.411,"GTM":0.418,"GIN":0.181,"GNB":0.108,"GUY":1.967,"HTI":0.059,"HND":0.472,"HKG":2.022,"HUN":5.967,"ISL":7.907,"IND":0.333,"IDN":0.252,"IRN":3.001,"IRQ":2.168,"IRL":6.089,"ISR":5.214,"ITA":4.727,"JAM":2.115,"JPN":5.397,"JOR":1.096,"KAZ":12.062,"KEN":0.268,"KIR":0.594,"KWT":33.661,"KGZ":4.297,"LAO":0.066,"LVA":6.214,"LBN":1.63,"LBR":0.634,"LBY":15.421,"LIE":3.672,"LTU":7.265,"LUX":36.397,"MAC":0.653,"MDG":0.145,"MWI":0.088,"MYS":1.083,"MLI":0.033,"MLT":1.971,"MRT":0.227,"MUS":0.798,"MEX":1.97,"MDA":6.315,"MNG":2.017,"MNE":1.722,"MSR":0.639,"MAR":0.392,"MOZ":0.352,"MMR":0.113,"NRU":7.503,"NPL":0.021,"NLD":8.905,"NCL":18.129,"NZL":4.891,"NIC":0.541,"NER":0.037,"NGA":0.124,"PRK":4.126,"MKD":2.767,"NOR":5.533,"OMN":0.256,"PAK":0.367,"PLW":6.929,"PAN":1.819,"PNG":0.21,"PRY":0.258,"PER":1.131,"PHL":0.624,"POL":8.597,"PRT":1.475,"QAT":77.104,"ROU":5.169,"RUS":10.196,"RWA":0.015,"SHN":0.649,"KNA":0.698,"LCA":0.364,"SPM":7.341,"VCT":0.234,"WSM":0.215,"STP":0.196,"SAU":8.858,"SEN":0.023,"SRB":3.23,"SYC":0.141,"SLE":0.139,"SGP":2.554,"SXM":191.425,"SVK":9.078,"SVN":3.863,"SLB":0.218,"SOM":0.043,"ZAF":6.583,"KOR":1.193,"SSD":0.075,"ESP":2.925,"LKA":0.276,"SDN":0.261,"SUR":4.092,"SWE":9.809,"CHE":5.931,"SYR":0.996,"TWN":1.698,"TJK":2.552,"TZA":0.131,"THA":0.502,"TGO":0.099,"TON":0.18,"TTO":4.166,"TUN":0.736,"TUR":1.038,"TKM":8.713,"UGA":0.101,"UKR":8.94,"ARE":6.228,"GBR":10.979,"USA":18.92,"URY":1.771,"UZB":5.021,"VUT":0.766,"VEN":6.13,"VNM":0.594,"YEM":1.739,"ZMB":1.123,"ZWE":1.301}