{"AFG":54.76,"DZA":81.71,"AGO":1.73,"ATG":8.06,"ARG":8.61,"ARM":34.82,"AUS":8.66,"AUT":9.97,"AZE":43.82,"BHR":234.76,"BRB":101.25,"BLR":5.97,"BEL":87.65,"BLZ":1.26,"BEN":0.98,"BOL":1.12,"BIH":2.48,"BWA":2.03,"BRA":2.67,"BRN":3.47,"BGR":43.12,"BFA":6.52,"BDI":10.42,"CMR":1.42,"CAN":4.31,"CPV":7.18,"CAF":0.31,"TCD":4.01,"CHL":7.62,"CHN":40.28,"COL":1.23,"COM":0.83,"COG":0.03,"CIV":6.29,"CUB":18.03,"CYP":20.5,"CZE":30.79,"COD":0.2,"DNK":19.1,"DJI":6.33,"DMA":8.3,"DOM":27.61,"ECU":6.48,"EGY":106.93,"SLV":9.51,"GNQ":0.17,"ERI":8.75,"EST":15.21,"SWZ":76.05,"FJI":0.29,"FIN":8.4,"FRA":28.47,"GAB":0.45,"GMB":2.02,"GEO":6.17,"DEU":61.3,"GHA":4.4,"GRC":18.46,"GTM":4.19,"GIN":0.86,"GNB":1.5,"GUY":3.71,"HTI":12.51,"HUN":10.02,"ISL":0.22,"IND":64.23,"IDN":16.02,"IRN":78.4,"IRQ":90.08,"IRL":4.5,"ISR":136.18,"ITA":38.23,"JAM":10.76,"JPN":40.2,"JOR":77.32,"KAZ":28.89,"KEN":14.95,"KWT":1993.42,"KGZ":62.88,"LVA":1.58,"LBN":40.28,"LSO":2.57,"LBR":0.24,"LBY":631.96,"LTU":19.96,"LUX":4.81,"MDG":11.2,"MWI":16.61,"MYS":2.91,"MDV":17.12,"MLI":7.84,"MLT":64.3,"MRT":15.08,"MUS":23.57,"MEX":25.8,"MDA":12.98,"MNG":3.65,"MAR":65.79,"MOZ":1.07,"MMR":5.8,"NAM":0.88,"NPL":8.36,"NLD":16.93,"NZL":2.97,"NIC":2.51,"NER":3.71,"NGA":8.18,"PRK":27.48,"MKD":16.04,"NOR":1.95,"OMN":90.79,"PAK":106.64,"PSE":38.58,"PNG":0.1,"PRY":0.5,"POL":41.31,"PRT":20.96,"PRI":19.75,"QAT":300.9,"REU":15.15,"ROU":8.48,"RUS":4.21,"RWA":5.64,"VCT":9.7,"STP":0.86,"SAU":832.64,"SEN":10.13,"SLE":0.45,"SGP":328.24,"SVK":4.88,"SOM":24.49,"ZAF":41.45,"KOR":82.96,"ESP":48.82,"LKA":91.15,"SUR":4.24,"SWE":3.86,"CHE":9.63,"SYR":138.52,"TJK":79.98,"TZA":11.81,"TGO":2.58,"TTO":19.36,"TUN":71.33,"TUR":30.41,"TKM":130.94,"UGA":3.16,"UKR":22.86,"ARE":1527.93,"GBR":21.42,"USA":30.08,"URY":9.88,"UZB":154.12,"VEN":3.68,"VNM":16.36,"YEM":162.87,"ZMB":2.87,"ZWE":37.61}